impyrialafouda/__init__.py
impyrialafouda/utils.py
impyrialafouda/length/__init__.py
impyrialafouda/length/api.py
impyrialafouda/length/core.py
impyrialafouda/weight/__init__.py
impyrialafouda/weight/api.py
impyrialafouda/weight/core.py
impyrialafouda-0.1.0.dist-info/LICENSE
impyrialafouda-0.1.0.dist-info/METADATA
impyrialafouda-0.1.0.dist-info/WHEEL
impyrialafouda-0.1.0.dist-info/top_level.txt
impyrialafouda-0.1.0.dist-info/RECORD
